graphalgo/__init__.py
graphalgo/conftest.py
graphalgo/convert.py
graphalgo/convert_matrix.py
graphalgo/exception.py
graphalgo/lazy_imports.py
graphalgo/relabel.py
graphalgo/algorithms/__init__.py
graphalgo/algorithms/asteroidal.py
graphalgo/algorithms/boundary.py
graphalgo/algorithms/bridges.py
graphalgo/algorithms/broadcasting.py
graphalgo/algorithms/chains.py
graphalgo/algorithms/chordal.py
graphalgo/algorithms/clique.py
graphalgo/algorithms/cluster.py
graphalgo/algorithms/communicability_alg.py
graphalgo/algorithms/core.py
graphalgo/algorithms/covering.py
graphalgo/algorithms/cuts.py
graphalgo/algorithms/cycles.py
graphalgo/algorithms/d_separation.py
graphalgo/algorithms/dag.py
graphalgo/algorithms/distance_measures.py
graphalgo/algorithms/distance_regular.py
graphalgo/algorithms/dominance.py
graphalgo/algorithms/dominating.py
graphalgo/algorithms/efficiency_measures.py
graphalgo/algorithms/euler.py
graphalgo/algorithms/graph_hashing.py
graphalgo/algorithms/graphical.py
graphalgo/algorithms/hierarchy.py
graphalgo/algorithms/hybrid.py
graphalgo/algorithms/isolate.py
graphalgo/algorithms/link_prediction.py
graphalgo/algorithms/lowest_common_ancestors.py
graphalgo/algorithms/matching.py
graphalgo/algorithms/mis.py
graphalgo/algorithms/moral.py
graphalgo/algorithms/node_classification.py
graphalgo/algorithms/non_randomness.py
graphalgo/algorithms/planar_drawing.py
graphalgo/algorithms/planarity.py
graphalgo/algorithms/polynomials.py
graphalgo/algorithms/reciprocity.py
graphalgo/algorithms/regular.py
graphalgo/algorithms/richclub.py
graphalgo/algorithms/similarity.py
graphalgo/algorithms/simple_paths.py
graphalgo/algorithms/smallworld.py
graphalgo/algorithms/smetric.py
graphalgo/algorithms/sparsifiers.py
graphalgo/algorithms/structuralholes.py
graphalgo/algorithms/summarization.py
graphalgo/algorithms/swap.py
graphalgo/algorithms/threshold.py
graphalgo/algorithms/time_dependent.py
graphalgo/algorithms/tournament.py
graphalgo/algorithms/triads.py
graphalgo-3.5.5.dist-info/licenses/LICENSE.txt
graphalgo-3.5.5.dist-info/METADATA
graphalgo-3.5.5.dist-info/WHEEL
graphalgo-3.5.5.dist-info/entry_points.txt
graphalgo-3.5.5.dist-info/top_level.txt
graphalgo-3.5.5.dist-info/RECORD
