Metadata-Version: 2.4
Name: graphalgo
Version: 3.5.5
Summary: Python package for creating and manipulating graphs and networks
Author-email: Aric Hagberg <hagberg@lanl.gov>
Maintainer-email: Graphalgo Developers <networkx-discuss@googlegroups.com>
License-Expression: BSD-3-Clause
Project-URL: Homepage, https://networkx.org/
Project-URL: Bug Tracker, https://github.com/taylortech75/graphalgo/issues
Project-URL: Source Code, https://github.com/taylortech75/graphalgo
Project-URL: Documentation, https://graphalgo.org/documentation/stable/
Keywords: Networks,Graph Theory,Mathematics,network,graph,discrete mathematics,math
Platform: Linux
Platform: Mac OSX
Platform: Windows
Platform: Unix
Classifier: Development Status :: 5 - Production/Stable
Classifier: Intended Audience :: Developers
Classifier: Intended Audience :: Science/Research
Classifier: Operating System :: OS Independent
Classifier: Programming Language :: Python :: 3
Classifier: Programming Language :: Python :: 3.11
Classifier: Programming Language :: Python :: 3.12
Classifier: Programming Language :: Python :: 3.13
Classifier: Programming Language :: Python :: 3 :: Only
Classifier: Topic :: Software Development :: Libraries :: Python Modules
Classifier: Topic :: Scientific/Engineering :: Bio-Informatics
Classifier: Topic :: Scientific/Engineering :: Information Analysis
Classifier: Topic :: Scientific/Engineering :: Mathematics
Classifier: Topic :: Scientific/Engineering :: Physics
Requires-Python: >=3.11
License-File: LICENSE.txt
Provides-Extra: default
Requires-Dist: numpy>=1.25; extra == "default"
Requires-Dist: scipy>=1.11.2; extra == "default"
Requires-Dist: matplotlib>=3.8; extra == "default"
Requires-Dist: pandas>=2.0; extra == "default"
Provides-Extra: developer
Requires-Dist: pre-commit>=4.1; extra == "developer"
Requires-Dist: mypy>=1.15; extra == "developer"
Provides-Extra: doc
Requires-Dist: sphinx>=8.0; extra == "doc"
Requires-Dist: pydata-sphinx-theme>=0.16; extra == "doc"
Requires-Dist: sphinx-gallery>=0.18; extra == "doc"
Requires-Dist: numpydoc>=1.8.0; extra == "doc"
Requires-Dist: pillow>=10; extra == "doc"
Requires-Dist: texext>=0.6.7; extra == "doc"
Requires-Dist: myst-nb>=1.1; extra == "doc"
Requires-Dist: intersphinx-registry; extra == "doc"
Provides-Extra: example
Requires-Dist: osmnx>=2.0.0; extra == "example"
Requires-Dist: momepy>=0.7.2; extra == "example"
Requires-Dist: contextily>=1.6; extra == "example"
Requires-Dist: seaborn>=0.13; extra == "example"
Requires-Dist: cairocffi>=1.7; extra == "example"
Requires-Dist: igraph>=0.11; extra == "example"
Requires-Dist: scikit-learn>=1.5; extra == "example"
Provides-Extra: extra
Requires-Dist: lxml>=4.6; extra == "extra"
Requires-Dist: pygraphviz>=1.14; extra == "extra"
Requires-Dist: pydot>=3.0.1; extra == "extra"
Requires-Dist: sympy>=1.10; extra == "extra"
Provides-Extra: test
Requires-Dist: pytest>=7.2; extra == "test"
Requires-Dist: pytest-cov>=4.0; extra == "test"
Requires-Dist: pytest-xdist>=3.0; extra == "test"
Provides-Extra: test-extras
Requires-Dist: pytest-mpl; extra == "test-extras"
Requires-Dist: pytest-randomly; extra == "test-extras"
Dynamic: license-file
